{
  "version": 1,
  "seriesID": "64000-question-spoof-1960",
  "title": "$64,000 Question Spoof",
  "yearStart": null,
  "yearEnd": null,
  "overview": null,
  "posterURL": "https://archive.org/services/img/Jack_Benny_64000_Dollar_Question_Spoof",
  "backdropURL": null,
  "genres": [],
  "networks": [],
  "creator": null,
  "seasons": [
    {
      "seasonNumber": null,
      "episodes": [
        {
          "archiveID": "Jack_Benny_64000_Dollar_Question_Spoof",
          "seasonNumber": null,
          "episodeNumber": null,
          "title": "$64,000 Question Spoof",
          "overview": null,
          "stillURL": "https://archive.org/services/img/Jack_Benny_64000_Dollar_Question_Spoof",
          "airDate": null,
          "year": null,
          "runtimeSeconds": null,
          "videoFile": {
            "name": "Jack_Benny_64000_Dollar_Question_Spoof.mp4",
            "format": "h.264",
            "sizeBytes": 151644288,
            "tier": 2
          },
          "downloadURL": "https://archive.org/download/Jack_Benny_64000_Dollar_Question_Spoof/Jack_Benny_64000_Dollar_Question_Spoof.mp4"
        }
      ]
    }
  ],
  "episodesCount": 1
}