{
  "version": 1,
  "seriesID": "alf-1960",
  "title": "ALF",
  "yearStart": null,
  "yearEnd": null,
  "overview": "A furry alien wiseguy comes to live with a terran family after crashing into their garage.",
  "posterURL": "https://image.tmdb.org/t/p/w500/shRed7ZrCRjdIMEYNx2YBVFkkNu.jpg",
  "backdropURL": "https://image.tmdb.org/t/p/w1280/ebLHsB8wsBnZnNa9UhGAqYeo33B.jpg",
  "genres": [],
  "networks": [
    "NBC"
  ],
  "creator": "Paul Fusco",
  "seasons": [
    {
      "seasonNumber": null,
      "episodes": [
        {
          "archiveID": "alf-complete",
          "seasonNumber": null,
          "episodeNumber": null,
          "title": "ALF (Complete Series)",
          "overview": null,
          "stillURL": "https://image.tmdb.org/t/p/w500/shRed7ZrCRjdIMEYNx2YBVFkkNu.jpg",
          "airDate": null,
          "year": null,
          "runtimeSeconds": null,
          "videoFile": {
            "name": "S04E25-26 - Project A.L.F..ia.mp4",
            "format": "h.264 IA",
            "sizeBytes": 1611973093,
            "tier": 2
          },
          "downloadURL": "https://archive.org/download/alf-complete/S04E25-26 - Project A.L.F..ia.mp4"
        }
      ]
    }
  ],
  "episodesCount": 1
}