{
  "version": 1,
  "seriesID": "boston-blackie-1953",
  "title": "Boston Blackie",
  "yearStart": 1953,
  "yearEnd": 1953,
  "overview": "Blackie and gal pal Mary, and their dog Whitey, solve lots of Los Angeles crimes before the cops can do it.",
  "posterURL": "https://image.tmdb.org/t/p/w500/vsy7pnp2i79ynlKXPrwmdCWxRia.jpg",
  "backdropURL": "https://image.tmdb.org/t/p/w1280/h9xt9iZPGXArooTE7Wur9QwMFoG.jpg",
  "genres": [],
  "networks": [],
  "creator": null,
  "seasons": [
    {
      "seasonNumber": 2,
      "episodes": [
        {
          "archiveID": "Boston_Blackie--The_Deadly_Payoff",
          "seasonNumber": 2,
          "episodeNumber": 18,
          "title": "Deadly Payoff",
          "overview": null,
          "stillURL": "https://image.tmdb.org/t/p/w500/vsy7pnp2i79ynlKXPrwmdCWxRia.jpg",
          "airDate": "1952-07-07",
          "year": 1953,
          "runtimeSeconds": null,
          "videoFile": {
            "name": "BostonBlackie218_Deadly_Payoff.mp4",
            "format": "h.264",
            "sizeBytes": 146274135,
            "tier": 2
          },
          "downloadURL": "https://archive.org/download/Boston_Blackie--The_Deadly_Payoff/BostonBlackie218_Deadly_Payoff.mp4"
        }
      ]
    }
  ],
  "episodesCount": 1
}