{
  "version": 1,
  "seriesID": "code-red-1981",
  "title": "Code Red",
  "yearStart": 1981,
  "yearEnd": 1981,
  "overview": null,
  "posterURL": "https://image.tmdb.org/t/p/w500/rOFXAg6lPrjLAw2NhtQYRrSpFXd.jpg",
  "backdropURL": null,
  "genres": [],
  "networks": [],
  "creator": null,
  "seasons": [
    {
      "seasonNumber": null,
      "episodes": [
        {
          "archiveID": "movie-of-the-week-code-red-1981-lorne-greene-julie-adams-andrew-stevens-kzd-j-3-ha-hnpo",
          "seasonNumber": null,
          "episodeNumber": null,
          "title": "Code Red (1981) - Feature-Length Pilot episode - Full",
          "overview": null,
          "stillURL": "https://image.tmdb.org/t/p/w500/rOFXAg6lPrjLAw2NhtQYRrSpFXd.jpg",
          "airDate": null,
          "year": 1981,
          "runtimeSeconds": null,
          "videoFile": {
            "name": "♦MOVIE OF THE WEEK♦ 'Code Red' (1981) Lorne GREENE, Julie ADAMS, Andrew STEVENS-KzdJ3HaHNPo.ia.mp4",
            "format": "h.264 IA",
            "sizeBytes": 422099630,
            "tier": 2
          },
          "downloadURL": "https://archive.org/download/movie-of-the-week-code-red-1981-lorne-greene-julie-adams-andrew-stevens-kzd-j-3-ha-hnpo/♦MOVIE OF THE WEEK♦ 'Code Red' (1981) Lorne GREENE, Julie ADAMS, Andrew STEVENS-KzdJ3HaHNPo.ia.mp4"
        }
      ]
    }
  ],
  "episodesCount": 1
}