{
  "version": 1,
  "seriesID": "doctor-at-large-1971",
  "title": "DOCTOR AT LARGE",
  "yearStart": 1971,
  "yearEnd": 1971,
  "overview": "Doctor at Large is a British television comedy series based on a set of books by Richard Gordon about the misadventures of a group of newly qualified doctors. The series follows directly from its predecessor Doctor in the House, and was produced by London Weekend Television in 1971.\n\nWriters for the Doctor at Large episodes were Bill Oddie, Graeme Garden, John Cleese, Graham Chapman, Bernard McKenna, Geoff Rowley, Andy Baker, Jonathan Lynn and David Yallop, as well as George Layton.",
  "posterURL": "https://image.tmdb.org/t/p/w500/fsGFLXLPNQizWj2OddxjCf3UOBi.jpg",
  "backdropURL": null,
  "genres": [],
  "networks": [
    "ITV1"
  ],
  "creator": null,
  "seasons": [
    {
      "seasonNumber": null,
      "episodes": [
        {
          "archiveID": "doctor-at-large-1971",
          "seasonNumber": null,
          "episodeNumber": null,
          "title": "DOCTOR AT LARGE (1971) (Full Series)",
          "overview": null,
          "stillURL": "https://image.tmdb.org/t/p/w500/fsGFLXLPNQizWj2OddxjCf3UOBi.jpg",
          "airDate": null,
          "year": 1971,
          "runtimeSeconds": null,
          "videoFile": {
            "name": "DOCTOR AT LARGE (1971)/26.Doctor at Large... Mr Moon.mp4",
            "format": "h.264",
            "sizeBytes": 150603953,
            "tier": 2
          },
          "downloadURL": "https://archive.org/download/doctor-at-large-1971/DOCTOR AT LARGE (1971)/26.Doctor at Large... Mr Moon.mp4"
        }
      ]
    }
  ],
  "episodesCount": 1
}