{
  "version": 1,
  "seriesID": "on-the-loose-1981",
  "title": "On The Loose",
  "yearStart": 1981,
  "yearEnd": 1981,
  "overview": null,
  "posterURL": "https://archive.org/services/img/saga-on-the-loose",
  "backdropURL": null,
  "genres": [],
  "networks": [],
  "creator": null,
  "seasons": [
    {
      "seasonNumber": null,
      "episodes": [
        {
          "archiveID": "saga-on-the-loose",
          "seasonNumber": null,
          "episodeNumber": null,
          "title": "On The Loose - Saga (1981)",
          "overview": null,
          "stillURL": "https://archive.org/services/img/saga-on-the-loose",
          "airDate": null,
          "year": 1981,
          "runtimeSeconds": null,
          "videoFile": {
            "name": "Saga- On The Loose.mp4",
            "format": "MPEG4",
            "sizeBytes": 20853173,
            "tier": 2
          },
          "downloadURL": "https://archive.org/download/saga-on-the-loose/Saga- On The Loose.mp4"
        }
      ]
    }
  ],
  "episodesCount": 1
}