{
  "version": 1,
  "seriesID": "one-life-to-live-july-30-1984-2021",
  "title": "One Life To Live (July 30, 1984",
  "yearStart": 2021,
  "yearEnd": 2021,
  "overview": null,
  "posterURL": "https://archive.org/services/img/one-life-to-live-july-30-1984",
  "backdropURL": null,
  "genres": [],
  "networks": [],
  "creator": null,
  "seasons": [
    {
      "seasonNumber": null,
      "episodes": [
        {
          "archiveID": "one-life-to-live-july-30-1984",
          "seasonNumber": null,
          "episodeNumber": null,
          "title": "One Life To Live (July 30, 1984)",
          "overview": null,
          "stillURL": "https://archive.org/services/img/one-life-to-live-july-30-1984",
          "airDate": null,
          "year": 2021,
          "runtimeSeconds": null,
          "videoFile": {
            "name": "One Life To Live (July 30, 1984).ia.mp4",
            "format": "h.264 IA",
            "sizeBytes": 812478323,
            "tier": 2
          },
          "downloadURL": "https://archive.org/download/one-life-to-live-july-30-1984/One Life To Live (July 30, 1984).ia.mp4"
        }
      ]
    }
  ],
  "episodesCount": 1
}