{
  "version": 1,
  "seriesID": "play-the-percentages-march-10-1980-2024",
  "title": "Play The Percentages (March 10, 1980",
  "yearStart": 2024,
  "yearEnd": 2024,
  "overview": null,
  "posterURL": "https://archive.org/services/img/play-the-percentages-march-10-1980",
  "backdropURL": null,
  "genres": [],
  "networks": [],
  "creator": null,
  "seasons": [
    {
      "seasonNumber": null,
      "episodes": [
        {
          "archiveID": "play-the-percentages-march-10-1980",
          "seasonNumber": null,
          "episodeNumber": null,
          "title": "Play The Percentages (March 10, 1980)",
          "overview": null,
          "stillURL": "https://archive.org/services/img/play-the-percentages-march-10-1980",
          "airDate": null,
          "year": 2024,
          "runtimeSeconds": null,
          "videoFile": {
            "name": "Play The Percentages (March 10, 1980).mp4",
            "format": "h.264",
            "sizeBytes": 132547276,
            "tier": 2
          },
          "downloadURL": "https://archive.org/download/play-the-percentages-march-10-1980/Play The Percentages (March 10, 1980).mp4"
        }
      ]
    }
  ],
  "episodesCount": 1
}