{
  "version": 1,
  "seriesID": "steven-banks-show-1994",
  "title": "Steven Banks Show",
  "yearStart": 1994,
  "yearEnd": 1994,
  "overview": null,
  "posterURL": null,
  "backdropURL": null,
  "genres": [],
  "networks": [],
  "creator": null,
  "seasons": [
    {
      "seasonNumber": 1,
      "episodes": [
        {
          "archiveID": "01stevenbanksshowrockauction",
          "seasonNumber": 1,
          "episodeNumber": 1,
          "title": "Steven Banks Show Episode 01 - Rock Auction",
          "overview": null,
          "stillURL": null,
          "airDate": null,
          "year": 1994,
          "runtimeSeconds": null,
          "videoFile": {
            "name": "01 Steven Banks Show - Rock Auction.mp4",
            "format": "h.264",
            "sizeBytes": 157222107,
            "tier": 1
          },
          "downloadURL": "https://archive.org/download/01stevenbanksshowrockauction/01 Steven Banks Show - Rock Auction.mp4"
        },
        {
          "archiveID": "02stevenbanksshowsidandernie",
          "seasonNumber": 1,
          "episodeNumber": 2,
          "title": "Steven Banks Show Episode 02 - Sid And Ernie",
          "overview": null,
          "stillURL": null,
          "airDate": null,
          "year": 1994,
          "runtimeSeconds": null,
          "videoFile": {
            "name": "02 Steven Banks Show - Sid and Ernie.mp4",
            "format": "h.264",
            "sizeBytes": 161288066,
            "tier": 1
          },
          "downloadURL": "https://archive.org/download/02stevenbanksshowsidandernie/02 Steven Banks Show - Sid and Ernie.mp4"
        },
        {
          "archiveID": "03stevenbanksshowvideodating",
          "seasonNumber": 1,
          "episodeNumber": 3,
          "title": "Steven Banks Show Episode 03 - Video Dating",
          "overview": null,
          "stillURL": null,
          "airDate": null,
          "year": 1994,
          "runtimeSeconds": null,
          "videoFile": {
            "name": "03 Steven Banks Show - Video Dating.mp4",
            "format": "h.264",
            "sizeBytes": 162435296,
            "tier": 1
          },
          "downloadURL": "https://archive.org/download/03stevenbanksshowvideodating/03 Steven Banks Show - Video Dating.mp4"
        },
        {
          "archiveID": "04stevenbanksshowphonetiquette",
          "seasonNumber": 1,
          "episodeNumber": 4,
          "title": "Steven Banks Show Episode 04 - Phonetiquette",
          "overview": null,
          "stillURL": null,
          "airDate": null,
          "year": 1994,
          "runtimeSeconds": null,
          "videoFile": {
            "name": "04 Steven Banks Show - Phonetiquette.mp4",
            "format": "h.264",
            "sizeBytes": 162479381,
            "tier": 1
          },
          "downloadURL": "https://archive.org/download/04stevenbanksshowphonetiquette/04 Steven Banks Show - Phonetiquette.mp4"
        },
        {
          "archiveID": "05stevenbanksshowbanksforthememories",
          "seasonNumber": 1,
          "episodeNumber": 5,
          "title": "Steven Banks Show Episode 05 - Banks For The Memories",
          "overview": null,
          "stillURL": null,
          "airDate": null,
          "year": 1994,
          "runtimeSeconds": null,
          "videoFile": {
            "name": "05 Steven Banks Show - Banks for the Memories.mp4",
            "format": "h.264",
            "sizeBytes": 162308284,
            "tier": 2
          },
          "downloadURL": "https://archive.org/download/05stevenbanksshowbanksforthememories/05 Steven Banks Show - Banks for the Memories.mp4"
        },
        {
          "archiveID": "06stevenbanksshowfauxclip",
          "seasonNumber": 1,
          "episodeNumber": 6,
          "title": "Steven Banks Show Episode 06 - Faux Clip",
          "overview": null,
          "stillURL": null,
          "airDate": null,
          "year": 1994,
          "runtimeSeconds": null,
          "videoFile": {
            "name": "06 Steven Banks Show - Faux Clip.mp4",
            "format": "h.264",
            "sizeBytes": 160246117,
            "tier": 1
          },
          "downloadURL": "https://archive.org/download/06stevenbanksshowfauxclip/06 Steven Banks Show - Faux Clip.mp4"
        },
        {
          "archiveID": "07stevenbanksshowrearcloset",
          "seasonNumber": 1,
          "episodeNumber": 7,
          "title": "Steven Banks Show Episode 07 - Rear Closet",
          "overview": null,
          "stillURL": null,
          "airDate": null,
          "year": 1994,
          "runtimeSeconds": null,
          "videoFile": {
            "name": "07 Steven Banks Show - Rear Closet.mp4",
            "format": "h.264",
            "sizeBytes": 160107243,
            "tier": 1
          },
          "downloadURL": "https://archive.org/download/07stevenbanksshowrearcloset/07 Steven Banks Show - Rear Closet.mp4"
        },
        {
          "archiveID": "08stevenbanksshowcowboywillie",
          "seasonNumber": 1,
          "episodeNumber": 8,
          "title": "Steven Banks Show Episode 08 - Cowboy Willie",
          "overview": null,
          "stillURL": null,
          "airDate": null,
          "year": 1994,
          "runtimeSeconds": null,
          "videoFile": {
            "name": "08 Steven Banks Show - Cowboy Willie.mp4",
            "format": "h.264",
            "sizeBytes": 163065693,
            "tier": 1
          },
          "downloadURL": "https://archive.org/download/08stevenbanksshowcowboywillie/08 Steven Banks Show - Cowboy Willie.mp4"
        },
        {
          "archiveID": "09stevenbanksshowsundayintheparkwithstuffy",
          "seasonNumber": 1,
          "episodeNumber": 9,
          "title": "Steven Banks Show Episode 09 - Sunday In The Park With Stuffy",
          "overview": null,
          "stillURL": null,
          "airDate": null,
          "year": 1994,
          "runtimeSeconds": null,
          "videoFile": {
            "name": "09 Steven Banks Show - Sunday in the Park with Stuffy.mp4",
            "format": "h.264",
            "sizeBytes": 159678328,
            "tier": 1
          },
          "downloadURL": "https://archive.org/download/09stevenbanksshowsundayintheparkwithstuffy/09 Steven Banks Show - Sunday in the Park with Stuffy.mp4"
        },
        {
          "archiveID": "10stevenbanksshowdustinthewind",
          "seasonNumber": 1,
          "episodeNumber": 10,
          "title": "Steven Banks Show Episode 10 - Dust In The Wind",
          "overview": null,
          "stillURL": null,
          "airDate": null,
          "year": 1994,
          "runtimeSeconds": null,
          "videoFile": {
            "name": "10 Steven Banks Show  - Dust In the Wind.mp4",
            "format": "h.264",
            "sizeBytes": 152308355,
            "tier": 1
          },
          "downloadURL": "https://archive.org/download/10stevenbanksshowdustinthewind/10 Steven Banks Show  - Dust In the Wind.mp4"
        },
        {
          "archiveID": "11stevenbanksshowmynameissteven",
          "seasonNumber": 1,
          "episodeNumber": 11,
          "title": "Steven Banks Show Episode 11 - My Name Is Steven",
          "overview": null,
          "stillURL": null,
          "airDate": null,
          "year": 1994,
          "runtimeSeconds": null,
          "videoFile": {
            "name": "11 Steven Banks Show - My Name is Steven.mp4",
            "format": "h.264",
            "sizeBytes": 161058727,
            "tier": 2
          },
          "downloadURL": "https://archive.org/download/11stevenbanksshowmynameissteven/11 Steven Banks Show - My Name is Steven.mp4"
        },
        {
          "archiveID": "12stevenbanksshowmissjanieregrets",
          "seasonNumber": 1,
          "episodeNumber": 12,
          "title": "Steven Banks Show Episode 12 - Miss Janie Regrets",
          "overview": null,
          "stillURL": null,
          "airDate": null,
          "year": 1994,
          "runtimeSeconds": null,
          "videoFile": {
            "name": "12 Steven Banks Show - Miss Janie Regrets.mp4",
            "format": "h.264",
            "sizeBytes": 160113093,
            "tier": 1
          },
          "downloadURL": "https://archive.org/download/12stevenbanksshowmissjanieregrets/12 Steven Banks Show - Miss Janie Regrets.mp4"
        },
        {
          "archiveID": "13stevenbanksshowthelastshow",
          "seasonNumber": 1,
          "episodeNumber": 13,
          "title": "Steven Banks Show Episode 13 - The Last Show",
          "overview": null,
          "stillURL": null,
          "airDate": null,
          "year": 1994,
          "runtimeSeconds": null,
          "videoFile": {
            "name": "13 Steven Banks Show - The Last Show.mp4",
            "format": "h.264",
            "sizeBytes": 162436230,
            "tier": 1
          },
          "downloadURL": "https://archive.org/download/13stevenbanksshowthelastshow/13 Steven Banks Show - The Last Show.mp4"
        }
      ]
    }
  ],
  "episodesCount": 13
}